birdhousebuilder.recipe.pycsw-0.3.0-py2.7-nspkg.pth
birdhousebuilder/recipe/pycsw/__init__.py
birdhousebuilder/recipe/pycsw/cswapp.py
birdhousebuilder/recipe/pycsw/gunicorn.conf.py
birdhousebuilder/recipe/pycsw/nginx.conf
birdhousebuilder/recipe/pycsw/pycsw.cfg
birdhousebuilder/recipe/pycsw/tests/__init__.py
birdhousebuilder/recipe/pycsw/tests/test_docs.py
birdhousebuilder.recipe.pycsw-0.3.0.dist-info/DESCRIPTION.rst
birdhousebuilder.recipe.pycsw-0.3.0.dist-info/METADATA
birdhousebuilder.recipe.pycsw-0.3.0.dist-info/RECORD
birdhousebuilder.recipe.pycsw-0.3.0.dist-info/WHEEL
birdhousebuilder.recipe.pycsw-0.3.0.dist-info/entry_points.txt
birdhousebuilder.recipe.pycsw-0.3.0.dist-info/metadata.json
birdhousebuilder.recipe.pycsw-0.3.0.dist-info/namespace_packages.txt
birdhousebuilder.recipe.pycsw-0.3.0.dist-info/pbr.json
birdhousebuilder.recipe.pycsw-0.3.0.dist-info/top_level.txt
