Metadata-Version: 2.0
Name: birdhousebuilder.recipe.pycsw
Version: 0.3.0
Summary: A Buildout recipe to install and configure pycsw Catalog Service (CSW) with Anaconda.
Home-page: https://github.com/bird-house/birdhousebuilder.recipe.pycsw
Author: Birdhouse
Author-email: UNKNOWN
License: BSD
Keywords: buildout recipe birdhouse pycsw geopython anaconda
Platform: UNKNOWN
Classifier: Framework :: Buildout
Classifier: Intended Audience :: Developers
Classifier: Topic :: Software Development :: Build Tools
Classifier: Topic :: Software Development :: Libraries :: Python Modules
Classifier: License :: OSI Approved :: BSD License
Requires-Dist: Mako
Requires-Dist: birdhousebuilder.recipe.conda
Requires-Dist: birdhousebuilder.recipe.nginx
Requires-Dist: birdhousebuilder.recipe.supervisor
Requires-Dist: setuptools
Requires-Dist: zc.buildout
Provides-Extra: tests
Requires-Dist: manuel; extra == 'tests'
Requires-Dist: zc.buildout; extra == 'tests'
Requires-Dist: zope.testing; extra == 'tests'
